bubblebox/__init__.py
bubblebox/binding_models.py
bubblebox/bubblebox.py
bubblebox/elements.py
bubblebox/flowbox.py
bubblebox/ising.py
bubblebox/lattice_models.py
bubblebox/mdbox.py
bubblebox/showcase.py
bubblebox/wavebox.py
BubbleBox-0.53.dist-info/LICENCE
BubbleBox-0.53.dist-info/METADATA
BubbleBox-0.53.dist-info/WHEEL
BubbleBox-0.53.dist-info/top_level.txt
BubbleBox-0.53.dist-info/RECORD
