Metadata-Version: 2.1
Name: BubbleBox
Version: 0.53
Summary: A molecular dynamics educational tool for Jupyter Notebooks
Home-page: https://github.uio.no/audunsh/bubblebox
Author: Audun Skau Hansen
Author-email: a.s.hansen@kjemi.uio.no
Classifier: Programming Language :: Python :: 3
Classifier: License :: OSI Approved :: MIT License
Classifier: Operating System :: OS Independent
License-File: LICENCE
Requires-Dist: numba
Requires-Dist: llvmlite
